mcp_ip2location/__init__.py
mcp_ip2location/main.py
mcp_ip2location/data/qqwry.dat
mcp_ip2location-0.1.7.dist-info/METADATA
mcp_ip2location-0.1.7.dist-info/WHEEL
mcp_ip2location-0.1.7.dist-info/entry_points.txt
mcp_ip2location-0.1.7.dist-info/RECORD
